{
  "job": {
    "channel": "blocking",
    "name": "47_seq_read_spdk",
    "numjobs": 1,
    "filename": "/dev/Nvme0n1",
    "block_size": 4096,
    "size":  66262417408,
    "termination": {
      "type": "iterations",
      "value": 16165652
    }
  },
  "operation": {
    "type": "constant",
    "operation": "read"
  },
  "access": {
    "type": "sequential"
  },
  "content": {
    "type": "constant"
  },
  "engine": {
    "type": "spdk",
    "open_flags": [
      "O_CREAT",
      "O_RDWR"
    ],
    "bdev_name": "Nvme0n1",
    "reactor_mask": "0xF",
    "spdk_threads": 1,
    "json_config_file": "/home/gsd/prismo/workloads/bdev/nvme_bdev.json"
  }
}
