{
  "job": {
    "channel": "blocking",
    "name": "53_barrier_fsync_spdk",
    "numjobs": 1,
    "filename": "/mnt/nvme/data/testfile_campaign",
    "block_size": 4096,
    "size":  66262417408,
    "metric": "base",
    "termination": {
      "type": "runtime",
      "value": 900000
    }
  },
  "operation": {
    "type": "sequence",
    "operations": [
      "write",
      "read",
      "write",
      "write"
    ],
    "barrier": [
      {
        "operation": "fsync",
        "trigger": "write",
        "threshold": 1024
      }
    ]
  },
  "access": {
    "type": "random"
  },
  "content": {
    "type": "random",
    "refill": false
  },
  "engine": {
    "type": "spdk",
    "open_flags": [
      "O_CREAT",
      "O_RDWR"
    ],
    "bdev_name": "Malloc0",
    "reactor_mask": "0xF",
    "spdk_threads": 1,
    "json_config_file": "/home/gsd/prismo/workloads/spdk/spdk_bdev.json"
  }
}
